[
  {
    "FromUserId": 2018,
    "ToUserId": 6,
    "TicketId": 1,
    "Content": "Great job fixing the payment issue!",
    "Rating": 5,
    "CreatedAt": "2023-11-06T15:00:00Z"
  },
  {
    "FromUserId": 2018,
    "ToUserId": 6,
    "TicketId": 2,
    "Content": "Reports now generate faster. Thanks!",
    "Rating": 4,
    "CreatedAt": "2023-11-07T11:30:00Z"
  },
  {
    "FromUserId": 2019,
    "ToUserId": 2016,
    "TicketId": 3,
    "Content": "Feature added successfully. Good work!",
    "Rating": 5,
    "CreatedAt": "2023-11-08T09:20:00Z"
  },
  {
    "FromUserId": 2019,
    "ToUserId": 2016,
    "TicketId": 4,
    "Content": "Thanks for your work on the security audit.",
    "Rating": 5,
    "CreatedAt": "2023-11-09T10:45:00Z"
  },
  {
    "FromUserId": 2020,
    "ToUserId": 2017,
    "TicketId": 5,
    "Content": "Prediction model fixed ahead of schedule. Great job!",
    "Rating": 5,
    "CreatedAt": "2023-11-08T14:30:00Z"
  },
  {
    "FromUserId": 2020,
    "ToUserId": 2017,
    "TicketId": 6,
    "Content": "Dashboard looks great. Well done!",
    "Rating": 4,
    "CreatedAt": "2023-11-09T16:15:00Z"
  },
  {
    "FromUserId": 2022,
    "ToUserId": 1009,
    "TicketId": 8,
    "Content": "Energy usage reports are spot on. Great job!",
    "Rating": 5,
    "CreatedAt": "2023-11-11T13:30:00Z"
  },
  {
    "FromUserId": 2023,
    "ToUserId": 1010,
    "TicketId": 9,
    "Content": "Quiz module is coming along well. Keep it up!",
    "Rating": 4,
    "CreatedAt": "2023-11-11T15:45:00Z"
  },
  {
    "FromUserId": 2018,
    "ToUserId": 6,
    "TicketId": 11,
    "Content": "Checkout process now runs smoothly. Thanks!",
    "Rating": 5,
    "CreatedAt": "2023-11-12T12:00:00Z"
  },
  {
    "FromUserId": 2019,
    "ToUserId": 1012,
    "TicketId": 12,
    "Content": "Thanks for fixing the record sync issues.",
    "Rating": 5,
    "CreatedAt": "2023-11-12T14:30:00Z"
  },
  {
    "FromUserId": 2022,
    "ToUserId": 1009,
    "TicketId": 14,
    "Content": "Energy overview report looks great. Well done!",
    "Rating": 5,
    "CreatedAt": "2023-11-13T16:00:00Z"
  },
  {
    "FromUserId": 2023,
    "ToUserId": 1010,
    "TicketId": 15,
    "Content": "Looking forward to the fix. Thanks for taking it up.",
    "Rating": 4,
    "CreatedAt": "2023-11-12T10:50:00Z"
  }
]
